lingualens/__init__.py
lingualens/analyzer.py
lingualens/metrics.py
lingualens/pipelines.py
lingualens/utils.py
text_compare/__init__.py
text_compare/analyzer.py
text_compare/metrics.py
text_compare/pipelines.py
text_compare/utils.py
linugalens-0.1.0.dist-info/LICENSE
linugalens-0.1.0.dist-info/METADATA
linugalens-0.1.0.dist-info/WHEEL
linugalens-0.1.0.dist-info/top_level.txt
linugalens-0.1.0.dist-info/RECORD
